{"id":1394,"title":"Nostalgia","original_title":"Ностальгия","poster":"/fCYSidPXp3LpDa9wlLNv0gZvjyF.jpg","backdrop":"/ePq5SQuGHbQ209pf4ViE747dGCw.jpg","overview":"A Russian poet and his interpreter travel to Italy to research the life of an 18th-century composer.","synopsis":"A Russian poet and his interpreter travel to Italy to research the life of an 18th-century composer.","runtime":125,"rating":7.8,"rt_rating":null,"release_date":"1983-05-01","trailer":"_a00N9fU1Mk","genre":"Drama,Romance","person":"Andrei Tarkovsky"}
