{"id":18477,"title":"The Hills Have Eyes Part 2","original_title":"The Hills Have Eyes Part 2","poster":"/cGLzgE2BTcHHyCXxS1lMxyY0iuc.jpg","backdrop":"/a9F2cldYpiwyOvR528D66wZ4git.jpg","overview":"A motocross team on their way to trial a new super-fuel head out across the desert lead by Rachel, who, unbeknownst to the rest of the group, is a survivor of the cannibal clan which menaced the Carter family several years before.","synopsis":"A motocross team on their way to trial a new super-fuel head out across the desert lead by Rachel, who, unbeknownst to the rest of the group, is a survivor of the cannibal clan which menaced the Carter family several years before.","runtime":90,"rating":4.432,"rt_rating":null,"release_date":"1985-08-02","trailer":"FcZHVs8lHTo","genre":"Horror,Thriller","person":"Wes Craven"}
