{"id":298723,"title":"Pro-Life","original_title":"Pro-Life","poster":"/iVUUEFgHzfW1qDNZ5MMsUewnPMt.jpg","backdrop":"/q9Y8MmCWTYmSysZykDsiH9Lynck.jpg","overview":"Angelique, a traumatized fifteen year old, is taken to an abortion clinic to end her pregnancy. However, her deeply religious father and three brothers are out to make sure the baby lives.","synopsis":"Angelique, a traumatized fifteen year old, is taken to an abortion clinic to end her pregnancy. However, her deeply religious father and three brothers are out to make sure the baby lives.","runtime":57,"rating":5.448,"rt_rating":null,"release_date":"2006-11-24","trailer":null,"genre":"Horror,Thriller,TV Movie","person":"John Carpenter"}
