{"id":311,"title":"Once Upon a Time in America","original_title":"Once Upon a Time in America","poster":"/i0enkzsL5dPeneWnjl1fCWm6L7k.jpg","backdrop":"/uPYa165sraN2c8gZBM9C47g3JoU.jpg","overview":"A former Prohibition-era Jewish gangster returns to the Lower East Side of Manhattan over thirty years later, where he once again must confront the ghosts and regrets of his old life.","synopsis":"A former Prohibition-era Jewish gangster returns to the Lower East Side of Manhattan over thirty years later, where he once again must confront the ghosts and regrets of his old life.","runtime":229,"rating":8.425,"rt_rating":null,"release_date":"1984-05-23","trailer":"lFw062jAYR0","genre":"Drama,Crime","person":"Sergio Leone"}
