{"id":38442,"title":"The Firemen's Ball","original_title":"Hoří, má panenko","poster":"/yylEjPttmTDar0o92StlrO5ghmw.jpg","backdrop":"/7ncgCjyUgL9EsRfbHVjl25jDHQa.jpg","overview":"The firemen of a provincial Czechoslovakian town throw a ball in honor of the old chief's retirement. There will be music and dancing, a beauty pageant and a raffle. The whole town will be in attendance. However, the proceedings are dogged by difficulty at every step. Workplace injuries, stolen prizes, a shortage of pretty girls... and fire.","synopsis":"The firemen of a provincial Czechoslovakian town throw a ball in honor of the old chief's retirement. There will be music and dancing, a beauty pageant and a raffle. The whole town will be in attendance. However, the proceedings are dogged by difficulty at every step. Workplace injuries, stolen prizes, a shortage of pretty girls... and fire.","runtime":73,"rating":7.1,"rt_rating":null,"release_date":"1967-12-15","trailer":"GfJI4LzLBUw","genre":"Drama,Comedy","person":"Miloš Forman"}
