{"id":452522,"title":"Twin Peaks","original_title":"Twin Peaks","poster":"/pA1gF7ivck5gnIQOTdGllKNfyJQ.jpg","backdrop":"/xqjGKLwLZeujg4fiBTOqhZkoL31.jpg","overview":"An idiosyncratic FBI agent investigates the murder of a young woman in the even more idiosyncratic town of Twin Peaks. (This standalone version of the series pilot was produced for the European VHS market and has an alternate, closed ending.)","synopsis":"An idiosyncratic FBI agent investigates the murder of a young woman in the even more idiosyncratic town of Twin Peaks. (This standalone version of the series pilot was produced for the European VHS market and has an alternate, closed ending.)","runtime":116,"rating":8.4,"rt_rating":null,"release_date":"1989-09-28","trailer":null,"genre":"Drama,Thriller,Mystery,TV Movie","person":"David Lynch"}
