{"id":575469,"title":"Land of the Free","original_title":"Land of the Free","poster":"/ckZNDRe4yOMFfr47MvTEpzh4hBY.jpg","backdrop":null,"overview":"Music video by The Killers performing Land of the Free. Copyright Island Records, a division of UMG Recordings, Inc.","synopsis":"Music video by The Killers performing Land of the Free. Copyright Island Records, a division of UMG Recordings, Inc.","runtime":5,"rating":0,"rt_rating":null,"release_date":"2019-01-15","trailer":null,"genre":null,"person":"Spike Lee"}
