{"id":73319,"title":"Visions of Eight","original_title":"Visions of Eight","poster":"/mzVkecyq9ZUh5kaF8caVwr7tHso.jpg","backdrop":"/tPLE5TmpCFcYKhf25foPNTwDikC.jpg","overview":"Eight acclaimed filmmakers bring their unique and differing perspectives to the 1972 Summer Olympic Games held in Munich. The segments include Lelouch's take on Olympic losers and their struggle to remain dignified even in the face of bitter disappointment and defeat; Zetterling's dramatic exploration of the world of weightlifting; and Pfleghar's piece on young Russian gymnast Ludmilla Tourischev's majestic performance on the uneven bars.","synopsis":"Eight acclaimed filmmakers bring their unique and differing perspectives to the 1972 Summer Olympic Games held in Munich. The segments include Lelouch's take on Olympic losers and their struggle to remain dignified even in the face of bitter disappointment and defeat; Zetterling's dramatic exploration of the world of weightlifting; and Pfleghar's piece on young Russian gymnast Ludmilla Tourischev's majestic performance on the uneven bars.","runtime":110,"rating":7.1,"rt_rating":null,"release_date":"1973-10-06","trailer":null,"genre":"Documentary","person":"Miloš Forman"}
