{"id":8054,"title":"The Imaginarium of Doctor Parnassus","original_title":"The Imaginarium of Doctor Parnassus","poster":"/DtrqQHa0wT9AWrk2WA9beROJJx.jpg","backdrop":"/vBw4z7l3NI32th7nR34zqRgdvXS.jpg","overview":"A travelling theatre company has more to it than meets the eye. It is an imaginary world commanded by the mind of Doctor Parnassus and the audience is in for more than just a show.","synopsis":"A travelling theatre company has more to it than meets the eye. It is an imaginary world commanded by the mind of Doctor Parnassus and the audience is in for more than just a show.","runtime":123,"rating":6.38,"rt_rating":null,"release_date":"2009-10-01","trailer":"eOL-wZSCn_g","genre":"Adventure,Fantasy,Mystery","person":"Terry Gilliam"}
