{"id":82327,"title":"Goodbye First Love","original_title":"Un amour de jeunesse","poster":"/qj1P2hZJxMO3bXiC39JxbTWTNa5.jpg","backdrop":"/146hnoa8ugfUtPgjPfl658vuTna.jpg","overview":"A 15-year-old discovers the joys and heartaches of first love with an older teen, but in the ensuing years, cannot seem to move past their breakup.","synopsis":"A 15-year-old discovers the joys and heartaches of first love with an older teen, but in the ensuing years, cannot seem to move past their breakup.","runtime":108,"rating":6.227,"rt_rating":null,"release_date":"2011-07-06","trailer":"7ZAH7bvJNRA","genre":"Drama,Romance","person":"Mia Hansen-Løve"}
