{"id":9571,"title":"Dazed and Confused","original_title":"Dazed and Confused","poster":"/msG9awbLhVZwv1Eh9Ge7SofMexW.jpg","backdrop":"/9Vygw4sIUyMZ3kY5mUmk1ccsDJc.jpg","overview":"The adventures of a group of Texas teens on their last day of school in 1976, centering on student Randall Floyd, who moves easily among stoners, jocks and geeks. Floyd is a star athlete, but he also likes smoking weed, which presents a conundrum when his football coach demands he sign a \"no drugs\" pledge.","synopsis":"The adventures of a group of Texas teens on their last day of school in 1976, centering on student Randall Floyd, who moves easily among stoners, jocks and geeks. Floyd is a star athlete, but he also likes smoking weed, which presents a conundrum when his football coach demands he sign a \"no drugs\" pledge.","runtime":102,"rating":7.354,"rt_rating":null,"release_date":"1993-09-24","trailer":"3aQuvPlcB-8","genre":"Drama,Comedy","person":"Richard Linklater"}
